postg/__init__.py
postg/postg.py
postg_q-0.1.2.dist-info/METADATA
postg_q-0.1.2.dist-info/WHEEL
postg_q-0.1.2.dist-info/top_level.txt
postg_q-0.1.2.dist-info/RECORD
