Metadata-Version: 2.4
Name: postg-q
Version: 0.1.2
Summary: Minimal PostgreSQL utility with psycopg2
Home-page: https://github.com/bigint001/postg
Author: bigint001 (Ivan Pohorilyi)
Author-email: thepatrickmaps@gmail.com
Classifier: Programming Language :: Python :: 3
Classifier: Operating System :: OS Independent
Requires-Dist: psycopg2-binary
Dynamic: author
Dynamic: author-email
Dynamic: classifier
Dynamic: description
Dynamic: description-content-type
Dynamic: home-page
Dynamic: requires-dist
Dynamic: summary
